<xMetaDiss:xMetaDiss xmlns:xMetaDiss="http://www.d-nb.de/standards/xmetadissplus/" xmlns:cc="http://www.d-nb.de/standards/cc/" xmlns:dc="http://purl.org/dc/elements/1.1/" xmlns:dcmitype="http://purl.org/dc/dcmitype/" xmlns:dcterms="http://purl.org/dc/terms/" xmlns:pc="http://www.d-nb.de/standards/pc/" xmlns:urn="http://www.d-nb.de/standards/urn/" xmlns:hdl="http://www.d-nb.de/standards/hdl/" xmlns:doi="http://www.d-nb.de/standards/doi/" xmlns:thesis="http://www.ndltd.org/standards/metadata/etdms/1.0/" xmlns:ddb="http://www.d-nb.de/standards/ddb/" xmlns:dini="http://www.d-nb.de/standards/xmetadissplus/type/" xmlns="http://www.d-nb.de/standards/subject/" xmlns:xsi="http://www.w3.org/2001/XMLSchema-instance" xmlns:doc="http://www.lyncode.com/xoai" xsi:schemaLocation="http://www.d-nb.de/standards/xmetadissplus/  http://files.dnb.de/standards/xmetadissplus/xmetadissplus.xsd"><id>1672</id>
   <dc:title xsi:type="ddb:titleISO639-2" lang="ger">Bewegliche Tragwerke</dc:title>
   <dc:creator xsi:type="pc:MetaPers">
      <pc:person>
         <pc:name type="nameUsedByThePerson">
            <pc:foreName>Katja</pc:foreName>
            <pc:surName>Wirfler</pc:surName>
         </pc:name>
      </pc:person>
   </dc:creator>
   <dc:creator xsi:type="pc:MetaPers">
      <pc:person>
         <pc:name type="nameUsedByThePerson">
            <pc:foreName>Martino Peña</pc:foreName>
            <pc:surName>Fernandez Serrano</pc:surName>
         </pc:name>
      </pc:person>
   </dc:creator>
   <dc:subject xsi:type="xMetaDiss:SWD">Faltwerk</dc:subject>
   <dc:subject xsi:type="xMetaDiss:noScheme">Prototypentwicklung</dc:subject>
   <dc:subject xsi:type="xMetaDiss:noScheme">Tragkonstruktion</dc:subject>
   <dc:subject xsi:type="xMetaDiss:noScheme">studentische Arbeiten</dc:subject>
   <dc:subject xsi:type="xMetaDiss:noScheme">Modellbau</dc:subject>
   <dc:subject xsi:type="xMetaDiss:DDC-SG">624</dc:subject>
   <dcterms:abstract xsi:type="ddb:contentISO639-2" lang="ger">Der erste Band Lehre 01 der neuen von Prof. Dr. Thorsten Weimar herausgegebenen Schriftenreihe Tragkonstruktion widmet sich dem Thema »Bewegliche Tragwerke« und dokumentiert studentische Arbeiten, die den Zusammenhang von Entwurf, gestalterischem Potential sowie erforderlicher Konstruktion bis hin zum analogen und digitalen Modell umfassen.&#13;
Seit 2014 wird das Wahlmodul »Bewegliche Tragwerke« vom Lehrstuhl für Tragkonstruktion im Department Architektur der Universität Siegen angeboten. Zentrales Ziel ist es dabei, den Studierenden ein allgemeines Verständnis für Tragkonstruktionen im Zusammenhang mit materialgerechtem Konstruieren und hohem architektonischen Anspruch zu vermitteln. Die Studierenden im Masterstudiengang Architektur entwerfen und entwickeln dazu faltbare und bewegliche Tragstrukturen. Dabei stehen für die Teilnehmer direkte Erfahrungen vom kreativen Umgang mit der Tragkonstruktion für die vorgegebene Aufgabe bis zur eigenständigen Umsetzung am Modell im Fokus.</dcterms:abstract>
   <dc:publisher xsi:type="cc:Publisher" type="dcterms:ISO3166" countryCode="DE">
      <cc:universityOrInstitution cc:GKD-Nr="509551-7">
         <cc:name>Universitätsbibliothek der Universität Siegen</cc:name>
         <cc:place>Siegen</cc:place>
      </cc:universityOrInstitution>
      <cc:address cc:Scheme="DIN5008">Adolf-Reichweinstr. 2, 57068 Siegen</cc:address>
   </dc:publisher>
   <dc:publisher xsi:type="cc:Publisher" type="dcterms:ISO3166" countryCode="DE">
      <cc:universityOrInstitution>
         <cc:name>universi – Universitätsverlag Siegen</cc:name>
         <cc:place>Siegen</cc:place>
      </cc:universityOrInstitution>
      <cc:address cc:Scheme="DIN5008">Am Eichenhang 50, 57076 Siegen</cc:address>
   </dc:publisher>
   <dc:contributor xsi:type="pc:Contributor" thesis:role="editor">
      <pc:person>
         <pc:name type="nameUsedByThePerson">
            <pc:foreName>Thorsten</pc:foreName>
            <pc:surName>Weimar</pc:surName>
         </pc:name>
      </pc:person>
   </dc:contributor>
   <dcterms:issued xsi:type="dcterms:W3CDTF">2019</dcterms:issued>
   <dc:type xsi:type="dini:PublType">book</dc:type>
   <dc:type xsi:type="dcterms:DCMIType">Text</dc:type>
   <dini:version_driver>publishedVersion</dini:version_driver>
   <dc:identifier xsi:type="urn:nbn">urn:nbn:de:hbz:467-16724</dc:identifier>
   <dc:source xsi:type="ddb:ISBN">978-3-96182-038-2</dc:source>
   <dc:language xsi:type="dcterms:ISO639-2">ger</dc:language>
   <dcterms:isPartOf xsi:type="ddb:noScheme">Schriftenreihe Tragkonstruktion;  Lehre 01</dcterms:isPartOf>
   <dc:rights xsi:type="dcterms:URI">http://creativecommons.org/licenses/by-sa/4.0/</dc:rights>
   <ddb:contact ddb:contactID="L6000-0732"/>
   <ddb:fileNumber>1</ddb:fileNumber>
   <ddb:fileProperties ddb:fileName="Bewegliche Tragwerke_Lehre 01.pdf" ddb:fileSize="47808863"/>
   <ddb:checksum ddb:type="MD5">ae6072ef7f80e53c400bb2fff742bc7c</ddb:checksum>
   <ddb:transfer ddb:type="dcterms:URI">https://dspace.ub.uni-siegen.de/bitstream/ubsi/1672/1/Bewegliche%20Tragwerke_Lehre%2001.pdf</ddb:transfer>
   <ddb:identifier ddb:type="URL">https://dspace.ub.uni-siegen.de/handle/ubsi/1672</ddb:identifier>
   <ddb:rights ddb:kind="free"/>
   <ddb:server>Universitätsbibliothek Siegen</ddb:server>
</xMetaDiss:xMetaDiss>