<xMetaDiss:xMetaDiss xmlns:xMetaDiss="http://www.d-nb.de/standards/xmetadissplus/" xmlns:cc="http://www.d-nb.de/standards/cc/" xmlns:dc="http://purl.org/dc/elements/1.1/" xmlns:dcmitype="http://purl.org/dc/dcmitype/" xmlns:dcterms="http://purl.org/dc/terms/" xmlns:pc="http://www.d-nb.de/standards/pc/" xmlns:urn="http://www.d-nb.de/standards/urn/" xmlns:hdl="http://www.d-nb.de/standards/hdl/" xmlns:doi="http://www.d-nb.de/standards/doi/" xmlns:thesis="http://www.ndltd.org/standards/metadata/etdms/1.0/" xmlns:ddb="http://www.d-nb.de/standards/ddb/" xmlns:dini="http://www.d-nb.de/standards/xmetadissplus/type/" xmlns="http://www.d-nb.de/standards/subject/" xmlns:xsi="http://www.w3.org/2001/XMLSchema-instance" xmlns:doc="http://www.lyncode.com/xoai" xsi:schemaLocation="http://www.d-nb.de/standards/xmetadissplus/  http://files.dnb.de/standards/xmetadissplus/xmetadissplus.xsd"><id>2081</id>
   <dc:title xsi:type="ddb:titleISO639-2" lang="ger">„Im Kleinsten zeigt sich die ganze Welt“. Verlebendigung von Puppen in Wort und Bild im Werk von Tony Schumacher</dc:title>
   <dc:title xsi:type="ddb:titleISO639-2" ddb:type="translated" lang="eng">“A whole world revealed – in the smallest of things”. Bringing dolls to life in words and pictures in the work of Tony Schumacher</dc:title>
   <dc:creator xsi:type="pc:MetaPers">
      <pc:person>
         <pc:name type="nameUsedByThePerson">
            <pc:foreName>Anna</pc:foreName>
            <pc:surName>Lehninger</pc:surName>
         </pc:name>
      </pc:person>
   </dc:creator>
   <dc:subject xsi:type="xMetaDiss:noScheme">Tony Schumacher</dc:subject>
   <dc:subject xsi:type="xMetaDiss:noScheme">Kinderliteratur</dc:subject>
   <dc:subject xsi:type="xMetaDiss:noScheme">19. Jahrhundert</dc:subject>
   <dc:subject xsi:type="xMetaDiss:noScheme">Illustration</dc:subject>
   <dc:subject xsi:type="xMetaDiss:noScheme">Autobiografie einer Sammlerin</dc:subject>
   <dc:subject xsi:type="xMetaDiss:noScheme">Puppensammlung</dc:subject>
   <dc:subject xsi:type="xMetaDiss:noScheme">Tony Schumacher</dc:subject>
   <dc:subject xsi:type="xMetaDiss:noScheme">Children’s literature</dc:subject>
   <dc:subject xsi:type="xMetaDiss:noScheme">19th century</dc:subject>
   <dc:subject xsi:type="xMetaDiss:noScheme">Illustration</dc:subject>
   <dc:subject xsi:type="xMetaDiss:noScheme">Autobiography of a collector</dc:subject>
   <dc:subject xsi:type="xMetaDiss:noScheme">Doll collection</dc:subject>
   <dcterms:abstract xsi:type="ddb:contentISO639-2" lang="ger">Puppen treten im Schaffen der deutschen Kinderbuchautorin (und -illustratorin) Tony Schumacher (1848-1931) in Haupt- und Nebenrollen auf. Schumacher war eine im 19. Jahrhundert äußerst populäre Schriftstellerin, die Dutzende Bücher publizierte und daneben antike Möbel, Krippenfiguren und vieles andere sammelte. In den autobiografischen Schriften der heute weitgehend vergessenen Autorin hat diese insbesondere ihrer über 200 Puppen zählenden Sammlung viel Platz eingeräumt. Darin erfuhr die reale Puppensammlung Transformationen in formal ganz unterschiedliche Bild- und Textnarrative. Die Analyse des Spiels der Autorin und Illustratorin mit Puppenkollektiv und Puppenindividuum, das subtil auf den Erzählinhalt abgestimmt und verbildlicht wird, ordnet exemplarisch Bilder und Texte aus der Zeit zwischen 1885 und 1930 biografisch und zeithistorisch ein.</dcterms:abstract>
   <dcterms:abstract xsi:type="ddb:contentISO639-2" lang="eng">Dolls appear in leading and supporting roles in the work of the German children’s book author (and illustrator) Tony Schumacher (1848-1931). Schumacher was an extremely popular writer in the 19th century who published dozens of books as well as being a collector of antique furniture, nativity figures and much more. In her autobiographical writings, this largely forgotten author places a particular emphasis on her collection of more than 200 dolls which undergo interesting narrative and pictural transformations. The playful approach of the author and illustrator with both individual dolls and doll collectives is analyzed and subtly coordinated with the narrative content and its visualization providing examples of images and texts from the period between 1885 and 1930 which are classified biographically and historically.</dcterms:abstract>
   <dc:publisher xsi:type="cc:Publisher" type="dcterms:ISO3166" countryCode="DE">
      <cc:universityOrInstitution cc:GKD-Nr="509551-7">
         <cc:name>Universitätsbibliothek der Universität Siegen</cc:name>
         <cc:place>Siegen</cc:place>
      </cc:universityOrInstitution>
      <cc:address cc:Scheme="DIN5008">Adolf-Reichweinstr. 2, 57068 Siegen</cc:address>
   </dc:publisher>
   <dcterms:issued xsi:type="dcterms:W3CDTF">2021</dcterms:issued>
   <dc:type xsi:type="dini:PublType">article</dc:type>
   <dc:type xsi:type="dcterms:DCMIType">Text</dc:type>
   <dini:version_driver>publishedVersion</dini:version_driver>
   <dc:identifier xsi:type="urn:nbn">urn:nbn:de:hbz:467-20818</dc:identifier>
   <dc:language xsi:type="dcterms:ISO639-2">ger</dc:language>
   <dcterms:isPartOf xsi:type="ddb:ZSTitelID">2625-5871</dcterms:isPartOf>
   <dcterms:isPartOf xsi:type="ddb:ZS-Ausgabe">1, 2021</dcterms:isPartOf>
   <dc:rights xsi:type="dcterms:URI">http://creativecommons.org/licenses/by-sa/4.0/</dc:rights>
   <ddb:contact ddb:contactID="L6000-0732"/>
   <ddb:fileNumber>1</ddb:fileNumber>
   <ddb:fileProperties ddb:fileName="Lehninger_Welt_Dedo4.pdf" ddb:fileSize="2458902"/>
   <ddb:checksum ddb:type="MD5">bfa60cd39cf98838f4615e8418479e0d</ddb:checksum>
   <ddb:transfer ddb:type="dcterms:URI">https://dspace.ub.uni-siegen.de/bitstream/ubsi/2081/1/Lehninger_Welt_Dedo4.pdf</ddb:transfer>
   <ddb:identifier ddb:type="URL">https://dedo.ub.uni-siegen.de/index.php/de_do/article/view/102</ddb:identifier>
   <ddb:identifier ddb:type="URL">https://dspace.ub.uni-siegen.de/handle/ubsi/2081</ddb:identifier>
   <ddb:rights ddb:kind="free"/>
   <ddb:server>Universitätsbibliothek Siegen</ddb:server>
</xMetaDiss:xMetaDiss>