<xMetaDiss:xMetaDiss xmlns:xMetaDiss="http://www.d-nb.de/standards/xmetadissplus/" xmlns:cc="http://www.d-nb.de/standards/cc/" xmlns:dc="http://purl.org/dc/elements/1.1/" xmlns:dcmitype="http://purl.org/dc/dcmitype/" xmlns:dcterms="http://purl.org/dc/terms/" xmlns:pc="http://www.d-nb.de/standards/pc/" xmlns:urn="http://www.d-nb.de/standards/urn/" xmlns:hdl="http://www.d-nb.de/standards/hdl/" xmlns:doi="http://www.d-nb.de/standards/doi/" xmlns:thesis="http://www.ndltd.org/standards/metadata/etdms/1.0/" xmlns:ddb="http://www.d-nb.de/standards/ddb/" xmlns:dini="http://www.d-nb.de/standards/xmetadissplus/type/" xmlns="http://www.d-nb.de/standards/subject/" xmlns:xsi="http://www.w3.org/2001/XMLSchema-instance" xmlns:doc="http://www.lyncode.com/xoai" xsi:schemaLocation="http://www.d-nb.de/standards/xmetadissplus/  http://files.dnb.de/standards/xmetadissplus/xmetadissplus.xsd"><id>85</id>
   <dc:title xsi:type="ddb:titleISO639-2" lang="ger">Computeralgebra - ein Weg über die Elektrodynamik zur Quantenphysik</dc:title>
   <dc:creator xsi:type="pc:MetaPers">
      <pc:person>
         <pc:name type="nameUsedByThePerson">
            <pc:foreName>Jochen</pc:foreName>
            <pc:surName>Geppert</pc:surName>
         </pc:name>
      </pc:person>
   </dc:creator>
   <dc:subject xsi:type="xMetaDiss:noScheme">Physikdidaktik</dc:subject>
   <dc:subject xsi:type="xMetaDiss:noScheme">Computeralgebra</dc:subject>
   <dc:subject xsi:type="xMetaDiss:noScheme">Quantenphysik</dc:subject>
   <dc:subject xsi:type="xMetaDiss:DDC-SG">530</dc:subject>
   <dcterms:abstract xsi:type="ddb:contentISO639-2" lang="ger">Die vorgelegte Arbeit stellt das Ergebnis einer dreijährigen Entwicklung und&#13;
Erprobung eines Quantenphysikkurses im Rahmen der Lehrerausbildung der Sekundarstufe&#13;
I an der Universität Siegen dar. Der Kurs ist Teil der Entwicklung des&#13;
Siegener Lehrkonzepts - ein auf der Anwendung des Computeralgebrasystems&#13;
Maple beruhender Ausbildungsgang durch welchen den Studierenden der Physik&#13;
Sek. I in einem sechssemestrigen Lehrgang ein Grundlagenstudium ermöglicht&#13;
werden soll. Das zu entwickelnde Lehrkonzept soll Vorlesungen über klassische&#13;
Mechanik und Elektrodynamik sowie Thermodynamik im Grundstudium umfassen.&#13;
Daran soll anschließend im Hauptstudium ein Kurs zur Einführung in&#13;
die Quantenphysik und in die nichtrelativistische Quantenmechanik erfolgen, die&#13;
beide in dieser Arbeit vorgestellt und in ihrer didaktischen Konzeption begründet&#13;
werden. Der Lehrgang soll dann durch einen Kurs zur Kern- bzw. Elementarteilchenphysik&#13;
abgerundet werden.&#13;
Der in dieser Arbeit vorgestellte Kurs zur Quantenphysik - bestehend aus den&#13;
Teilen Einführung in die Quantenphysik sowie Quantenmechanik ist so angelegt,&#13;
dass er sich nicht nur an Lehramtsstudierende richtet, sondern ebenfalls für interessierte&#13;
Schülerinnen und Schüler der Sek. II geeignet ist. Der Kurs ist so&#13;
angelegt, dass er als Vorlesung an der Hochschule sowie im Selbststudium als interaktives&#13;
Lehrbuch durchgearbeitet werden kann.Teile des Kurses sind ebenfalls&#13;
im Unterricht der Sek. II einsetzbar.</dcterms:abstract>
   <dcterms:abstract xsi:type="ddb:contentISO639-2" lang="eng">The thesis contains the results of a development of a course in quantum mechanics&#13;
for students of teachership and mastership at the Siegen university. The&#13;
course is part of the development of the Siegener teaching concept which uses&#13;
Maple for presenting and visualization of abstract mathematical results. The&#13;
aim of the Siegener teaching concept is a complete course in physics using Maple&#13;
(classical mechanics, elektrodynamics, thermodynamics, quantum mechanics and&#13;
particle physics) for students of teachership and mastership .&#13;
The course in quantum mechanics is not only suitable for students of physics but&#13;
for pupils. It can be used for a course at the university and at home. Some parts&#13;
of the course can be used for instruction at secondary school.</dcterms:abstract>
   <dc:publisher xsi:type="cc:Publisher" type="dcterms:ISO3166" countryCode="DE">
      <cc:universityOrInstitution cc:GKD-Nr="509551-7">
         <cc:name>Universitätsbibliothek der Universität Siegen</cc:name>
         <cc:place>Siegen</cc:place>
      </cc:universityOrInstitution>
      <cc:address cc:Scheme="DIN5008">Adolf-Reichweinstr. 2, 57068 Siegen</cc:address>
   </dc:publisher>
   <dcterms:dateAccepted xsi:type="dcterms:W3CDTF">2004-10-19</dcterms:dateAccepted>
   <dcterms:issued xsi:type="dcterms:W3CDTF">2004</dcterms:issued>
   <dc:type xsi:type="dini:PublType">doctoralThesis</dc:type>
   <dc:type xsi:type="dcterms:DCMIType">Text</dc:type>
   <dini:version_driver>publishedVersion</dini:version_driver>
   <dc:identifier xsi:type="urn:nbn">urn:nbn:de:hbz:467-853</dc:identifier>
   <dc:language xsi:type="dcterms:ISO639-2">ger</dc:language>
   <dc:rights xsi:type="dcterms:URI">https://dspace.ub.uni-siegen.de/static/license.txt</dc:rights>
   <thesis:degree>
      <thesis:level>thesis.doctoral</thesis:level>
      <thesis:grantor xsi:type="cc:Corporate" type="dcterms:ISO3166" countryCode="DE">
         <cc:universityOrInstitution>
            <cc:name>Universität Siegen</cc:name>
            <cc:place>Siegen</cc:place>
            <cc:department>
               <cc:name>Fachbereich 7, Physik</cc:name>
               <cc:place>Siegen</cc:place>
            </cc:department>
         </cc:universityOrInstitution>
      </thesis:grantor>
   </thesis:degree>
   <ddb:contact ddb:contactID="L6000-0732"/>
   <ddb:fileNumber>2</ddb:fileNumber>
   <ddb:fileProperties ddb:fileName="geppert.pdf" ddb:fileSize="2049298"/>
   <ddb:fileProperties ddb:fileName="cd.zip" ddb:fileSize="13612489"/>
   <ddb:identifier ddb:type="URL">https://dspace.ub.uni-siegen.de/handle/ubsi/85</ddb:identifier>
   <ddb:rights ddb:kind="free"/>
   <ddb:server>Universitätsbibliothek Siegen</ddb:server>
</xMetaDiss:xMetaDiss>